cde_submit_migration/__init__.py
cde_submit_migration/main.py
cde_submit_migration/migration.py
cde_submit_migration-0.14.0.dist-info/WHEEL
cde_submit_migration-0.14.0.dist-info/entry_points.txt
cde_submit_migration-0.14.0.dist-info/METADATA
cde_submit_migration-0.14.0.dist-info/RECORD
