Metadata-Version: 2.3
Name: cde-submit-migration
Version: 0.14.0
Summary: Lightweight spark-based migration runner for executing SQL migrations on Spark catalog tables in Cloudera Data Engineering (CDE).
Author: Domovic, Matija (PPN)
Author-email: Domovic, Matija (PPN) <matija.domovic@porsche.digital>
Requires-Dist: click>=8.3.1
Requires-Dist: pyspark==3.5.1
Requires-Python: >=3.11
